Metadata-Version: 2.1
Name: eigd
Version: 1.0.0
Summary: Tools for eigenvector derivatives
Home-page: https://github.com/smdogroup/eigd
Author: 
Author-email: graeme.kennedy@ae.gatech.edu
License: Apache License, Version 2.0
License-File: LICENSE
